{
  "grado": "primaria-2",
  "materia": "matematicas",
  "bloques": [
    {
      "bloque": 1,
      "nombre": "Numeros hasta 100",
      "meses": "Agosto-Septiembre",
      "url": "/primaria-2/matematicas/bloque-1"
    },
    {
      "bloque": 2,
      "nombre": "Sumas y restas",
      "meses": "Octubre-Noviembre",
      "url": "/primaria-2/matematicas/bloque-2"
    },
    {
      "bloque": 3,
      "nombre": "Multiplicacion basica",
      "meses": "Diciembre-Enero",
      "url": "/primaria-2/matematicas/bloque-3"
    },
    {
      "bloque": 4,
      "nombre": "Figuras planas",
      "meses": "Febrero-Marzo",
      "url": "/primaria-2/matematicas/bloque-4"
    },
    {
      "bloque": 5,
      "nombre": "Medidas y fracciones basicas",
      "meses": "Abril-Junio",
      "url": "/primaria-2/matematicas/bloque-5"
    }
  ]
}